pytest_fixturecollection.py
pytest_fixturecollection-0.1.2.dist-info/LICENSE
pytest_fixturecollection-0.1.2.dist-info/METADATA
pytest_fixturecollection-0.1.2.dist-info/WHEEL
pytest_fixturecollection-0.1.2.dist-info/entry_points.txt
pytest_fixturecollection-0.1.2.dist-info/top_level.txt
pytest_fixturecollection-0.1.2.dist-info/RECORD
