Metadata-Version: 2.1
Name: pytest-fixturecollection
Version: 0.1.2
Summary: A pytest plugin to collect tests based on fixtures being used by tests
Home-page: https://github.com/RedhatQE/pytest-fixturecollection
Author: Jitendra Yejare
Author-email: jyejare@redhat.com
Maintainer: Jitendra Yejare
Maintainer-email: jyejare@redhat.com
License: BSD-3
Classifier: Development Status :: 4 - Beta
Classifier: Framework :: Pytest
Classifier: Intended Audience :: Developers
Classifier: Topic :: Software Development :: Testing
Classifier: Programming Language :: Python
Classifier: Programming Language :: Python :: 3.9
Classifier: Programming Language :: Python :: 3.10
Classifier: Programming Language :: Python :: 3.11
Classifier: Programming Language :: Python :: 3 :: Only
Classifier: Programming Language :: Python :: Implementation :: CPython
Classifier: Programming Language :: Python :: Implementation :: PyPy
Classifier: Operating System :: OS Independent
Classifier: License :: OSI Approved :: BSD License
Requires-Python: >=3.9
License-File: LICENSE
Requires-Dist: pytest >=3.5.0
Provides-Extra: test
Requires-Dist: tox ~=3.18 ; extra == 'test'
Requires-Dist: flake8 ; extra == 'test'
